{
  "type": "HealthAndBeautyBusiness",
  "name": "Élodie Bedon",
  "short": "Magnétisme, Soins et Rééquilibrage énergétique, Lithothérapie, État élargi de conscience, Tarologie, Massage énergétique · Magnétiseuse à Clermont-Ferrand",
  "description": "Magnétisme, Soins et Rééquilibrage énergétique, Lithothérapie, État élargi de conscience, Tarologie à Clermont-Ferrand",
  "email": "elodie.bedon@hotmail.fr",
  "phone": "+33768485414",
  "areaServed": "Clermont-Ferrand",
  "analytics": {
    "googleTagManagerId": "GTM-TJ5B3CPF"
  },
  "address": {
    "name": "Cabinet Psy'Jaude",
    "street": "2 avenue Julien, place Jaude",
    "postalCode": "63000",
    "locality": "Clermont-Ferrand",
    "country": "FR"
  },
  "hours": [
    { "day": "monday", "ranges": [
        ["09:30", "12:30"],
        ["13:30", "18:30"]
      ] 
    },
    { "day": "tuesday", "ranges": [
        ["09:30", "12:30"],
        ["13:30", "18:30"]
      ] 
    },
    {
      "day": "wednesday",
      "ranges": [
        ["09:30", "12:30"],
        ["13:30", "18:30"]
      ]
    },
    {
      "day": "thursday",
      "ranges": [
        ["09:30", "12:30"],
        ["13:30", "18:30"]
      ]
    },
    {
      "day": "friday",
      "ranges": [
        ["09:30", "12:30"],
        ["13:30", "18:30"]
      ]
    },
    { 
      "day": "saturday", 
      "ranges": [
        ["09:30", "12:30"]
      ] 
    },
    { "day": "sunday", "ranges": [] }
  ],
  "social": [
    {
      "network": "Instagram",
      "url": "https://www.instagram.com/elodiebedonmagnetisme/",
      "icon": "instagram.svg"
    },
    {
      "network": "Facebook",
      "url": "https://www.facebook.com/elodiebedon.magnetisme",
      "icon": "facebook.svg"
    },
    {
      "network": "LinkedIn",
      "url": "https://www.linkedin.com/in/elodie-bedon-156a45184/",
      "icon": "linkedin.svg"
    },
    {
      "network": "X (ex-Twitter)",
      "url": "https://www.x.com/ebmagnetisme",
      "icon": "x.svg"
    },
    {
      "network": "Google Maps",
      "url": "https://share.google/XEB0AxWITa7WWOsF9",
      "icon": "maps.svg"
    }
  ]
}
